{
  "category": "ontology_completeness",
  "label": "Ontology Completeness",
  "score": 71,
  "deductions": [
    {
      "finding": "2 critical ontology gaps remain",
      "evidence": "ontology-gap-report.json: gap-entity-neighbor-1, gap-rel-2",
      "reason": "Required entities, relationships, claims, or decision points are missing per CKO §8–§9.",
      "severity": "critical",
      "category": "ontology_completeness",
      "suggestedFix": "Resolve critical gaps via assigned factory agents before publication review.",
      "impact": 15
    },
    {
      "finding": "1 high-priority ontology gaps",
      "evidence": "Gap kinds: missing_relationship",
      "reason": "High-priority gaps block maturity level advancement.",
      "severity": "high",
      "category": "ontology_completeness",
      "impact": 2,
      "suggestedFix": "Schedule gap-resolution work items from ontology-work-plan.json."
    },
    {
      "finding": "Missing entity requirements (1)",
      "evidence": "1 gaps of kind missing_entity",
      "reason": "Ontology contract requires complete entity coverage.",
      "severity": "medium",
      "category": "ontology_completeness",
      "impact": 1,
      "suggestedFix": "Run the matching builder agent for missing_entity."
    },
    {
      "finding": "Missing relationship requirements (3)",
      "evidence": "3 gaps of kind missing_relationship",
      "reason": "Ontology contract requires complete relationship coverage.",
      "severity": "medium",
      "category": "ontology_completeness",
      "impact": 3,
      "suggestedFix": "Run the matching builder agent for missing_relationship."
    },
    {
      "finding": "No classification system present",
      "evidence": "0 classification entities in merged draft",
      "reason": "Fracture diagnoses require classification when one exists clinically.",
      "severity": "high",
      "category": "ontology_completeness",
      "suggestedFix": "Link has_classification and has_grade edges to a classification system.",
      "impact": 8
    }
  ],
  "metrics": {
    "totalGaps": 6,
    "criticalGaps": 2,
    "highGaps": 1,
    "anatomyStructures": 32,
    "classificationEntities": 0,
    "completenessRatio": 0.8
  },
  "recommendations": [
    "Resolve critical gaps via assigned factory agents before publication review.",
    "Schedule gap-resolution work items from ontology-work-plan.json.",
    "Link has_classification and has_grade edges to a classification system."
  ]
}
