{
  "packetId": "ev-packet-982c2544",
  "topicId": "orthopaedic-anatomy",
  "createdAt": "2026-07-08T21:20:25.182Z",
  "packetVersion": "1.0.0",
  "sourceCount": 8,
  "evidenceItemCount": 11,
  "signalCount": 4,
  "proposalCount": 420,
  "gapCount": 47,
  "warningCount": 3,
  "collectorsRun": [
    "static-prepare-collector",
    "curriculum-node-collector",
    "anki-signal-collector",
    "orthobullets-metadata-collector",
    "caseprep-link-collector",
    "canonical-snapshot-collector",
    "proposal-history-collector",
    "review-history-collector",
    "quality-signal-collector"
  ],
  "databaseModified": false
}
