{
  "generatedAt": "2026-07-16T02:32:31.872Z",
  "gaps": [
    {
      "id": "gap-rel-1",
      "kind": "missing_relationship",
      "priority": "high",
      "confidence": 0.92,
      "reason": "Adult Reconstruction Anatomy Hub missing outbound part_of (0/1).",
      "requiredReviewer": "curator",
      "maturityImpact": 0.1,
      "ontologyRule": "anatomy.pred.hierarchy",
      "anchorEntitySlug": "adult-reconstruction-anatomy-hub",
      "subjectSlug": "adult-reconstruction-anatomy-hub",
      "predicate": "part_of"
    },
    {
      "id": "gap-entity-neighbor-2",
      "kind": "missing_entity",
      "priority": "critical",
      "confidence": 0.95,
      "reason": "Aseptic Loosening of THA neighborhood has 1/3 anatomy_structure entities.",
      "requiredReviewer": "clinical_expert",
      "maturityImpact": 0.15,
      "ontologyRule": "condition.anatomy.min_structures",
      "anchorEntitySlug": "aseptic-loosening-tha",
      "entityType": "anatomy_structure"
    },
    {
      "id": "gap-entity-neighbor-3",
      "kind": "missing_entity",
      "priority": "high",
      "confidence": 0.95,
      "reason": "Aseptic Loosening of THA neighborhood has 0/1 classification_system entities.",
      "requiredReviewer": "curator",
      "maturityImpact": 0.1,
      "ontologyRule": "condition.classification.system",
      "anchorEntitySlug": "aseptic-loosening-tha",
      "entityType": "classification_system"
    },
    {
      "id": "gap-rel-4",
      "kind": "missing_relationship",
      "priority": "critical",
      "confidence": 0.92,
      "reason": "Aseptic Loosening of THA missing outbound injured_in (0/1).",
      "requiredReviewer": "clinical_expert",
      "maturityImpact": 0.15,
      "ontologyRule": "condition.pred.injured_in",
      "anchorEntitySlug": "aseptic-loosening-tha",
      "subjectSlug": "aseptic-loosening-tha",
      "predicate": "injured_in"
    },
    {
      "id": "gap-rel-5",
      "kind": "missing_relationship",
      "priority": "high",
      "confidence": 0.92,
      "reason": "Aseptic Loosening of THA missing outbound at_risk_structure (0/1).",
      "requiredReviewer": "attending",
      "maturityImpact": 0.1,
      "ontologyRule": "condition.pred.at_risk_structure",
      "anchorEntitySlug": "aseptic-loosening-tha",
      "subjectSlug": "aseptic-loosening-tha",
      "predicate": "at_risk_structure"
    },
    {
      "id": "gap-rel-6",
      "kind": "missing_relationship",
      "priority": "critical",
      "confidence": 0.92,
      "reason": "Aseptic Loosening of THA missing outbound has_classification (0/1).",
      "requiredReviewer": "clinical_expert",
      "maturityImpact": 0.15,
      "ontologyRule": "condition.pred.has_classification",
      "anchorEntitySlug": "aseptic-loosening-tha",
      "subjectSlug": "aseptic-loosening-tha",
      "predicate": "has_classification"
    },
    {
      "id": "gap-rel-7",
      "kind": "missing_relationship",
      "priority": "high",
      "confidence": 0.92,
      "reason": "Aseptic Loosening of THA missing outbound has_grade (0/1).",
      "requiredReviewer": "curator",
      "maturityImpact": 0.1,
      "ontologyRule": "condition.pred.has_grade",
      "anchorEntitySlug": "aseptic-loosening-tha",
      "subjectSlug": "aseptic-loosening-tha",
      "predicate": "has_grade"
    },
    {
      "id": "gap-rel-8",
      "kind": "missing_relationship",
      "priority": "high",
      "confidence": 0.92,
      "reason": "Aseptic Loosening of THA missing outbound treated_by (0/1).",
      "requiredReviewer": "curator",
      "maturityImpact": 0.1,
      "ontologyRule": "condition.pred.treated_by",
      "anchorEntitySlug": "aseptic-loosening-tha",
      "subjectSlug": "aseptic-loosening-tha",
      "predicate": "treated_by"
    },
    {
      "id": "gap-claim-9",
      "kind": "missing_claim",
      "priority": "high",
      "confidence": 0.88,
      "reason": "Aseptic Loosening of THA has 0/3 L1 claims.",
      "requiredReviewer": "curator",
      "maturityImpact": 0.1,
      "ontologyRule": "condition.claims.l1",
      "anchorEntitySlug": "aseptic-loosening-tha",
      "claimType": "fact|board_trap|imaging_point|cognitive_trap"
    },
    {
      "id": "gap-claim-type-10",
      "kind": "missing_claim",
      "priority": "medium",
      "confidence": 0.75,
      "reason": "Aseptic Loosening of THA missing claim type: fact.",
      "requiredReviewer": "none",
      "maturityImpact": 0.05,
      "ontologyRule": "condition.claims.l1.fact",
      "anchorEntitySlug": "aseptic-loosening-tha",
      "claimType": "fact"
    },
    {
      "id": "gap-claim-type-11",
      "kind": "missing_claim",
      "priority": "medium",
      "confidence": 0.75,
      "reason": "Aseptic Loosening of THA missing claim type: board_trap.",
      "requiredReviewer": "none",
      "maturityImpact": 0.05,
      "ontologyRule": "condition.claims.l1.board_trap",
      "anchorEntitySlug": "aseptic-loosening-tha",
      "claimType": "board_trap"
    },
    {
      "id": "gap-claim-type-12",
      "kind": "missing_claim",
      "priority": "medium",
      "confidence": 0.75,
      "reason": "Aseptic Loosening of THA missing claim type: imaging_point.",
      "requiredReviewer": "none",
      "maturityImpact": 0.05,
      "ontologyRule": "condition.claims.l1.imaging_point",
      "anchorEntitySlug": "aseptic-loosening-tha",
      "claimType": "imaging_point"
    },
    {
      "id": "gap-claim-type-13",
      "kind": "missing_claim",
      "priority": "medium",
      "confidence": 0.75,
      "reason": "Aseptic Loosening of THA missing claim type: cognitive_trap.",
      "requiredReviewer": "none",
      "maturityImpact": 0.05,
      "ontologyRule": "condition.claims.l1.cognitive_trap",
      "anchorEntitySlug": "aseptic-loosening-tha",
      "claimType": "cognitive_trap"
    },
    {
      "id": "gap-dp-14",
      "kind": "missing_decision_point",
      "priority": "critical",
      "confidence": 0.9,
      "reason": "Aseptic Loosening of THA has 0/1 decision points.",
      "requiredReviewer": "attending",
      "maturityImpact": 0.15,
      "ontologyRule": "condition.dp.management",
      "anchorEntitySlug": "aseptic-loosening-tha"
    },
    {
      "id": "gap-dp-pattern-15",
      "kind": "missing_decision_point",
      "priority": "critical",
      "confidence": 0.85,
      "reason": "Aseptic Loosening of THA missing decision point pattern: operative_indication.",
      "requiredReviewer": "attending",
      "maturityImpact": 0.15,
      "ontologyRule": "condition.dp.management.operative_indication",
      "anchorEntitySlug": "aseptic-loosening-tha",
      "decisionPointPattern": "operative_indication"
    },
    {
      "id": "gap-dp-pattern-16",
      "kind": "missing_decision_point",
      "priority": "critical",
      "confidence": 0.85,
      "reason": "Aseptic Loosening of THA missing decision point pattern: nonoperative_eligible.",
      "requiredReviewer": "attending",
      "maturityImpact": 0.15,
      "ontologyRule": "condition.dp.management.nonoperative_eligible",
      "anchorEntitySlug": "aseptic-loosening-tha",
      "decisionPointPattern": "nonoperative_eligible"
    },
    {
      "id": "gap-meta-rel-17",
      "kind": "missing_metadata",
      "priority": "medium",
      "confidence": 0.9,
      "reason": "1 clinical_importance gaps on Aseptic Loosening of THA injured_in/has_imaging_finding/at_risk_structure edges.",
      "requiredReviewer": "none",
      "maturityImpact": 0.05,
      "ontologyRule": "condition.meta.clinical_importance",
      "anchorEntitySlug": "aseptic-loosening-tha",
      "metadataField": "clinical_importance",
      "predicate": "injured_in|has_imaging_finding|at_risk_structure"
    },
    {
      "id": "gap-rel-18",
      "kind": "missing_relationship",
      "priority": "medium",
      "confidence": 0.92,
      "reason": "Arthroplasty Implant Concepts Hub missing inbound involves_anatomy (0/1).",
      "requiredReviewer": "none",
      "maturityImpact": 0.05,
      "ontologyRule": "biomechanics.inbound",
      "anchorEntitySlug": "implant-concepts-hub",
      "predicate": "involves_anatomy",
      "objectSlug": "implant-concepts-hub"
    },
    {
      "id": "gap-claim-19",
      "kind": "missing_claim",
      "priority": "medium",
      "confidence": 0.88,
      "reason": "Arthroplasty Implant Concepts Hub has 0/1 L1 claims.",
      "requiredReviewer": "none",
      "maturityImpact": 0.05,
      "ontologyRule": "biomechanics.claims",
      "anchorEntitySlug": "implant-concepts-hub",
      "claimType": "fact|anatomy_pearl"
    },
    {
      "id": "gap-claim-type-20",
      "kind": "missing_claim",
      "priority": "medium",
      "confidence": 0.75,
      "reason": "Arthroplasty Implant Concepts Hub missing claim type: fact.",
      "requiredReviewer": "none",
      "maturityImpact": 0.05,
      "ontologyRule": "biomechanics.claims.fact",
      "anchorEntitySlug": "implant-concepts-hub",
      "claimType": "fact"
    },
    {
      "id": "gap-claim-type-21",
      "kind": "missing_claim",
      "priority": "medium",
      "confidence": 0.75,
      "reason": "Arthroplasty Implant Concepts Hub missing claim type: anatomy_pearl.",
      "requiredReviewer": "none",
      "maturityImpact": 0.05,
      "ontologyRule": "biomechanics.claims.anatomy_pearl",
      "anchorEntitySlug": "implant-concepts-hub",
      "claimType": "anatomy_pearl"
    },
    {
      "id": "gap-entity-neighbor-22",
      "kind": "missing_entity",
      "priority": "critical",
      "confidence": 0.95,
      "reason": "Revision Arthroplasty neighborhood has 0/1 anatomy_structure entities.",
      "requiredReviewer": "clinical_expert",
      "maturityImpact": 0.15,
      "ontologyRule": "procedure.anatomy",
      "anchorEntitySlug": "revision-arthroplasty",
      "entityType": "anatomy_structure"
    },
    {
      "id": "gap-rel-23",
      "kind": "missing_relationship",
      "priority": "critical",
      "confidence": 0.92,
      "reason": "Revision Arthroplasty missing outbound involves_anatomy (0/1).",
      "requiredReviewer": "clinical_expert",
      "maturityImpact": 0.15,
      "ontologyRule": "procedure.pred.involves_anatomy",
      "anchorEntitySlug": "revision-arthroplasty",
      "subjectSlug": "revision-arthroplasty",
      "predicate": "involves_anatomy"
    },
    {
      "id": "gap-rel-24",
      "kind": "missing_relationship",
      "priority": "high",
      "confidence": 0.92,
      "reason": "Revision Arthroplasty missing outbound at_risk_structure (0/1).",
      "requiredReviewer": "attending",
      "maturityImpact": 0.1,
      "ontologyRule": "procedure.pred.at_risk_structure",
      "anchorEntitySlug": "revision-arthroplasty",
      "subjectSlug": "revision-arthroplasty",
      "predicate": "at_risk_structure"
    },
    {
      "id": "gap-asset-card-25",
      "kind": "missing_asset_link",
      "priority": "medium",
      "confidence": 0.8,
      "reason": "5 Anki mappings exist but no card link proposals in neighborhood.",
      "requiredReviewer": "curator",
      "maturityImpact": 0.05,
      "ontologyRule": "neighborhood.assets.cards",
      "anchorEntitySlug": "aseptic-loosening-tha"
    },
    {
      "id": "gap-asset-question-26",
      "kind": "missing_asset_link",
      "priority": "medium",
      "confidence": 0.8,
      "reason": "22 question mappings exist but no question link proposals.",
      "requiredReviewer": "curator",
      "maturityImpact": 0.05,
      "ontologyRule": "neighborhood.assets.questions",
      "anchorEntitySlug": "aseptic-loosening-tha"
    },
    {
      "id": "gap-biomech-claim-27",
      "kind": "missing_claim",
      "priority": "medium",
      "confidence": 0.82,
      "reason": "Biomechanics concept Arthroplasty Implant Concepts Hub has no teaching claim (e.g., mortise instability).",
      "requiredReviewer": "clinical_expert",
      "maturityImpact": 0.05,
      "ontologyRule": "biomechanics.claims",
      "anchorEntitySlug": "implant-concepts-hub",
      "claimType": "fact"
    },
    {
      "id": "gap-proc-approach-28",
      "kind": "missing_relationship",
      "priority": "medium",
      "confidence": 0.78,
      "reason": "Procedure Revision Arthroplasty missing uses_approach edge.",
      "requiredReviewer": "clinical_expert",
      "maturityImpact": 0.05,
      "ontologyRule": "procedure.pred.uses_approach",
      "anchorEntitySlug": "revision-arthroplasty",
      "subjectSlug": "revision-arthroplasty",
      "predicate": "uses_approach"
    }
  ],
  "summary": {
    "total": 28,
    "byKind": {
      "missing_relationship": 10,
      "missing_entity": 3,
      "missing_claim": 9,
      "missing_decision_point": 3,
      "missing_metadata": 1,
      "missing_asset_link": 2
    },
    "byPriority": {
      "high": 7,
      "critical": 8,
      "medium": 13
    }
  }
}
