{
  "generatedAt": "2026-07-05T22:33:19.279Z",
  "gaps": [
    {
      "id": "gap-rel-1",
      "kind": "missing_relationship",
      "priority": "high",
      "confidence": 0.92,
      "reason": "Lower Extremity Trauma Anatomy Hub missing outbound part_of (0/1).",
      "requiredReviewer": "curator",
      "maturityImpact": 0.1,
      "ontologyRule": "anatomy.pred.hierarchy",
      "anchorEntitySlug": "lower-extremity-trauma-anatomy-hub",
      "subjectSlug": "lower-extremity-trauma-anatomy-hub",
      "predicate": "part_of"
    },
    {
      "id": "gap-rel-2",
      "kind": "missing_relationship",
      "priority": "high",
      "confidence": 0.92,
      "reason": "Acetabular Fracture missing outbound at_risk_structure (0/1).",
      "requiredReviewer": "attending",
      "maturityImpact": 0.1,
      "ontologyRule": "condition.pred.at_risk_structure",
      "anchorEntitySlug": "acetabular-fracture",
      "subjectSlug": "acetabular-fracture",
      "predicate": "at_risk_structure"
    },
    {
      "id": "gap-rel-3",
      "kind": "missing_relationship",
      "priority": "high",
      "confidence": 0.92,
      "reason": "Acetabular Fracture missing outbound has_grade (0/1).",
      "requiredReviewer": "curator",
      "maturityImpact": 0.1,
      "ontologyRule": "condition.pred.has_grade",
      "anchorEntitySlug": "acetabular-fracture",
      "subjectSlug": "acetabular-fracture",
      "predicate": "has_grade"
    },
    {
      "id": "gap-rel-4",
      "kind": "missing_relationship",
      "priority": "high",
      "confidence": 0.92,
      "reason": "Acetabular Fracture missing outbound treated_by (0/1).",
      "requiredReviewer": "curator",
      "maturityImpact": 0.1,
      "ontologyRule": "condition.pred.treated_by",
      "anchorEntitySlug": "acetabular-fracture",
      "subjectSlug": "acetabular-fracture",
      "predicate": "treated_by"
    },
    {
      "id": "gap-claim-5",
      "kind": "missing_claim",
      "priority": "high",
      "confidence": 0.88,
      "reason": "Acetabular Fracture has 0/3 L1 claims.",
      "requiredReviewer": "curator",
      "maturityImpact": 0.1,
      "ontologyRule": "condition.claims.l1",
      "anchorEntitySlug": "acetabular-fracture",
      "claimType": "fact|board_trap|imaging_point|cognitive_trap"
    },
    {
      "id": "gap-claim-type-6",
      "kind": "missing_claim",
      "priority": "medium",
      "confidence": 0.75,
      "reason": "Acetabular Fracture missing claim type: fact.",
      "requiredReviewer": "none",
      "maturityImpact": 0.05,
      "ontologyRule": "condition.claims.l1.fact",
      "anchorEntitySlug": "acetabular-fracture",
      "claimType": "fact"
    },
    {
      "id": "gap-claim-type-7",
      "kind": "missing_claim",
      "priority": "medium",
      "confidence": 0.75,
      "reason": "Acetabular Fracture missing claim type: board_trap.",
      "requiredReviewer": "none",
      "maturityImpact": 0.05,
      "ontologyRule": "condition.claims.l1.board_trap",
      "anchorEntitySlug": "acetabular-fracture",
      "claimType": "board_trap"
    },
    {
      "id": "gap-claim-type-8",
      "kind": "missing_claim",
      "priority": "medium",
      "confidence": 0.75,
      "reason": "Acetabular Fracture missing claim type: imaging_point.",
      "requiredReviewer": "none",
      "maturityImpact": 0.05,
      "ontologyRule": "condition.claims.l1.imaging_point",
      "anchorEntitySlug": "acetabular-fracture",
      "claimType": "imaging_point"
    },
    {
      "id": "gap-claim-type-9",
      "kind": "missing_claim",
      "priority": "medium",
      "confidence": 0.75,
      "reason": "Acetabular Fracture missing claim type: cognitive_trap.",
      "requiredReviewer": "none",
      "maturityImpact": 0.05,
      "ontologyRule": "condition.claims.l1.cognitive_trap",
      "anchorEntitySlug": "acetabular-fracture",
      "claimType": "cognitive_trap"
    },
    {
      "id": "gap-dp-10",
      "kind": "missing_decision_point",
      "priority": "critical",
      "confidence": 0.9,
      "reason": "Acetabular Fracture has 0/1 decision points.",
      "requiredReviewer": "attending",
      "maturityImpact": 0.15,
      "ontologyRule": "condition.dp.management",
      "anchorEntitySlug": "acetabular-fracture"
    },
    {
      "id": "gap-dp-pattern-11",
      "kind": "missing_decision_point",
      "priority": "critical",
      "confidence": 0.85,
      "reason": "Acetabular Fracture missing decision point pattern: operative_indication.",
      "requiredReviewer": "attending",
      "maturityImpact": 0.15,
      "ontologyRule": "condition.dp.management.operative_indication",
      "anchorEntitySlug": "acetabular-fracture",
      "decisionPointPattern": "operative_indication"
    },
    {
      "id": "gap-dp-pattern-12",
      "kind": "missing_decision_point",
      "priority": "critical",
      "confidence": 0.85,
      "reason": "Acetabular Fracture missing decision point pattern: nonoperative_eligible.",
      "requiredReviewer": "attending",
      "maturityImpact": 0.15,
      "ontologyRule": "condition.dp.management.nonoperative_eligible",
      "anchorEntitySlug": "acetabular-fracture",
      "decisionPointPattern": "nonoperative_eligible"
    },
    {
      "id": "gap-meta-rel-13",
      "kind": "missing_metadata",
      "priority": "medium",
      "confidence": 0.9,
      "reason": "2 clinical_importance gaps on Acetabular Fracture injured_in/has_imaging_finding/at_risk_structure edges.",
      "requiredReviewer": "none",
      "maturityImpact": 0.05,
      "ontologyRule": "condition.meta.clinical_importance",
      "anchorEntitySlug": "acetabular-fracture",
      "metadataField": "clinical_importance",
      "predicate": "injured_in|has_imaging_finding|at_risk_structure"
    },
    {
      "id": "gap-rel-14",
      "kind": "missing_relationship",
      "priority": "high",
      "confidence": 0.92,
      "reason": "Acetabular ORIF missing outbound at_risk_structure (0/1).",
      "requiredReviewer": "attending",
      "maturityImpact": 0.1,
      "ontologyRule": "procedure.pred.at_risk_structure",
      "anchorEntitySlug": "acetabular-orif",
      "subjectSlug": "acetabular-orif",
      "predicate": "at_risk_structure"
    },
    {
      "id": "gap-meta-rel-15",
      "kind": "missing_metadata",
      "priority": "medium",
      "confidence": 0.9,
      "reason": "1 context_relevance gaps on Acetabular ORIF involves_anatomy/at_risk_structure edges.",
      "requiredReviewer": "none",
      "maturityImpact": 0.05,
      "ontologyRule": "procedure.meta.context",
      "anchorEntitySlug": "acetabular-orif",
      "metadataField": "context_relevance",
      "predicate": "involves_anatomy|at_risk_structure"
    },
    {
      "id": "gap-entity-neighbor-16",
      "kind": "missing_entity",
      "priority": "high",
      "confidence": 0.95,
      "reason": "Judet-Letournel Classification neighborhood has 0/2 classification_grade entities.",
      "requiredReviewer": "curator",
      "maturityImpact": 0.1,
      "ontologyRule": "classification.grades",
      "anchorEntitySlug": "judet-letournel-classification",
      "entityType": "classification_grade"
    },
    {
      "id": "gap-asset-card-17",
      "kind": "missing_asset_link",
      "priority": "medium",
      "confidence": 0.8,
      "reason": "24 Anki mappings exist but no card link proposals in neighborhood.",
      "requiredReviewer": "curator",
      "maturityImpact": 0.05,
      "ontologyRule": "neighborhood.assets.cards",
      "anchorEntitySlug": "acetabular-fracture"
    },
    {
      "id": "gap-asset-question-18",
      "kind": "missing_asset_link",
      "priority": "medium",
      "confidence": 0.8,
      "reason": "74 question mappings exist but no question link proposals.",
      "requiredReviewer": "curator",
      "maturityImpact": 0.05,
      "ontologyRule": "neighborhood.assets.questions",
      "anchorEntitySlug": "acetabular-fracture"
    },
    {
      "id": "gap-proc-approach-19",
      "kind": "missing_relationship",
      "priority": "medium",
      "confidence": 0.78,
      "reason": "Procedure Acetabular ORIF missing uses_approach edge.",
      "requiredReviewer": "clinical_expert",
      "maturityImpact": 0.05,
      "ontologyRule": "procedure.pred.uses_approach",
      "anchorEntitySlug": "acetabular-orif",
      "subjectSlug": "acetabular-orif",
      "predicate": "uses_approach"
    }
  ],
  "summary": {
    "total": 19,
    "byKind": {
      "missing_relationship": 6,
      "missing_claim": 5,
      "missing_decision_point": 3,
      "missing_metadata": 2,
      "missing_entity": 1,
      "missing_asset_link": 2
    },
    "byPriority": {
      "high": 7,
      "medium": 9,
      "critical": 3
    }
  }
}
