{
  "category": "graph_integrity",
  "label": "Graph Integrity",
  "score": 84,
  "deductions": [
    {
      "finding": "57 orphan entities with no relationships",
      "evidence": "Slugs: hip-center-of-rotation, acetabulum, calcar, collateral-ligaments, common-peroneal-nerve, cruciate-ligaments, distal-femur, extensor-mechanism, femoral-diaphysis, femoral-head, femoral-neck, femoral-nerve, femur, gluteus-medius, gluteus-minimus, greater-trochanter, hip-joint, intertrochanteric-region, lesser-trochanter, medial-femoral-circumflex-artery, patella, patellar-tendon, pelvis, popliteal-artery, proximal-femur, proximal-femur-anatomy-hub, quadriceps-tendon, sciatic-nerve, tibia, tibial-plateau, bearing-surface-selection, compartment-syndrome, distal-femur-fracture, femoral-neck-fracture, femoral-shaft-fracture, hip-prosthetic-joint-infection, intertrochanteric-fracture, knee-osteoarthritis, knee-prosthetic-joint-infection, periprosthetic-joint-infection, subtrochanteric-fracture, tibial-shaft-fracture, cement-mantle, cemented-fixation, press-fit-fixation, acetabular-component, femoral-component, femoral-stem, patellar-component, polyethylene-liner, tibial-baseplate, tibial-insert, adverse-local-tissue-reaction, polyethylene-wear-osteolysis, revision-arthroplasty, total-knee-arthroplasty, unicompartmental-knee-arthroplasty",
      "reason": "Orphan entities cannot be traversed by products and indicate incomplete graph wiring.",
      "severity": "high",
      "category": "graph_integrity",
      "affectedSlugs": [
        "hip-center-of-rotation",
        "acetabulum",
        "calcar",
        "collateral-ligaments",
        "common-peroneal-nerve",
        "cruciate-ligaments",
        "distal-femur",
        "extensor-mechanism",
        "femoral-diaphysis",
        "femoral-head",
        "femoral-neck",
        "femoral-nerve",
        "femur",
        "gluteus-medius",
        "gluteus-minimus",
        "greater-trochanter",
        "hip-joint",
        "intertrochanteric-region",
        "lesser-trochanter",
        "medial-femoral-circumflex-artery",
        "patella",
        "patellar-tendon",
        "pelvis",
        "popliteal-artery",
        "proximal-femur",
        "proximal-femur-anatomy-hub",
        "quadriceps-tendon",
        "sciatic-nerve",
        "tibia",
        "tibial-plateau",
        "bearing-surface-selection",
        "compartment-syndrome",
        "distal-femur-fracture",
        "femoral-neck-fracture",
        "femoral-shaft-fracture",
        "hip-prosthetic-joint-infection",
        "intertrochanteric-fracture",
        "knee-osteoarthritis",
        "knee-prosthetic-joint-infection",
        "periprosthetic-joint-infection",
        "subtrochanteric-fracture",
        "tibial-shaft-fracture",
        "cement-mantle",
        "cemented-fixation",
        "press-fit-fixation",
        "acetabular-component",
        "femoral-component",
        "femoral-stem",
        "patellar-component",
        "polyethylene-liner",
        "tibial-baseplate",
        "tibial-insert",
        "adverse-local-tissue-reaction",
        "polyethylene-wear-osteolysis",
        "revision-arthroplasty",
        "total-knee-arthroplasty",
        "unicompartmental-knee-arthroplasty"
      ],
      "suggestedFix": "Add inbound or outbound clinical/anatomy edges, or merge duplicates.",
      "impact": 8
    },
    {
      "finding": "29 disconnected anatomy structures",
      "evidence": "Disconnected: acetabulum, calcar, collateral-ligaments, common-peroneal-nerve, cruciate-ligaments, distal-femur, extensor-mechanism, femoral-diaphysis, femoral-head, femoral-neck, femoral-nerve, femur, gluteus-medius, gluteus-minimus, greater-trochanter, hip-joint, intertrochanteric-region, lesser-trochanter, medial-femoral-circumflex-artery, patella, patellar-tendon, pelvis, popliteal-artery, proximal-femur, proximal-femur-anatomy-hub, quadriceps-tendon, sciatic-nerve, tibia, tibial-plateau",
      "reason": "Anatomy must connect to the condition graph for educational traversal.",
      "severity": "high",
      "category": "graph_integrity",
      "affectedSlugs": [
        "acetabulum",
        "calcar",
        "collateral-ligaments",
        "common-peroneal-nerve",
        "cruciate-ligaments",
        "distal-femur",
        "extensor-mechanism",
        "femoral-diaphysis",
        "femoral-head",
        "femoral-neck",
        "femoral-nerve",
        "femur",
        "gluteus-medius",
        "gluteus-minimus",
        "greater-trochanter",
        "hip-joint",
        "intertrochanteric-region",
        "lesser-trochanter",
        "medial-femoral-circumflex-artery",
        "patella",
        "patellar-tendon",
        "pelvis",
        "popliteal-artery",
        "proximal-femur",
        "proximal-femur-anatomy-hub",
        "quadriceps-tendon",
        "sciatic-nerve",
        "tibia",
        "tibial-plateau"
      ],
      "suggestedFix": "Add involves_anatomy, injured_in, or part_of edges from condition/procedure anchors.",
      "impact": 8
    }
  ],
  "metrics": {
    "entityCount": 64,
    "relationshipCount": 7,
    "orphanCount": 57,
    "danglingEdgeCount": 0,
    "duplicateLabelGroups": 0,
    "invalidPredicateCount": 0,
    "validationRate": 1
  },
  "recommendations": [
    "Add inbound or outbound clinical/anatomy edges, or merge duplicates.",
    "Add involves_anatomy, injured_in, or part_of edges from condition/procedure anchors."
  ]
}
